collective.roster-2.3.1-py3.6-nspkg.pth
collective/roster/__init__.py
collective/roster/configure.zcml
collective/roster/interfaces.py
collective/roster/person.py
collective/roster/roster.py
collective/roster/testing.py
collective/roster/upgrades.py
collective/roster/upgrades.zcml
collective/roster/utils.py
collective/roster/validators.zcml
collective/roster/behaviors/__init__.py
collective/roster/behaviors/auto_roles.py
collective/roster/behaviors/auto_roles.zcml
collective/roster/behaviors/configure.zcml
collective/roster/behaviors/contact_info.py
collective/roster/behaviors/contact_info.zcml
collective/roster/behaviors/groups.py
collective/roster/behaviors/groups.zcml
collective/roster/behaviors/groups_as_subjects.py
collective/roster/behaviors/groups_as_subjects.zcml
collective/roster/behaviors/interfaces.py
collective/roster/behaviors/office_info.py
collective/roster/behaviors/office_info.zcml
collective/roster/behaviors/related_persons.py
collective/roster/behaviors/related_persons.zcml
collective/roster/behaviors/subject_info.py
collective/roster/behaviors/subject_info.zcml
collective/roster/behaviors/templates/contact_info_viewlet.pt
collective/roster/behaviors/templates/office_info_viewlet.pt
collective/roster/behaviors/templates/related_content_viewlet.pt
collective/roster/behaviors/templates/roster_groups_gallery_view.pt
collective/roster/behaviors/templates/roster_groups_view.pt
collective/roster/behaviors/templates/subject_info_viewlet.pt
collective/roster/browser/__init__.py
collective/roster/browser/configure.zcml
collective/roster/browser/interfaces.py
collective/roster/browser/person.py
collective/roster/browser/roster.py
collective/roster/browser/static/bundle.css
collective/roster/browser/static/bundle.js
collective/roster/browser/static/css/person.css
collective/roster/browser/static/css/roster.css
collective/roster/browser/templates/person_biography_viewlet.pt
collective.roster-2.3.1.dist-info/DESCRIPTION.rst
collective.roster-2.3.1.dist-info/METADATA
collective.roster-2.3.1.dist-info/RECORD
collective.roster-2.3.1.dist-info/WHEEL
collective.roster-2.3.1.dist-info/entry_points.txt
collective.roster-2.3.1.dist-info/metadata.json
collective.roster-2.3.1.dist-info/namespace_packages.txt
collective.roster-2.3.1.dist-info/top_level.txt
