Metadata-Version: 2.0
Name: collective.roster
Version: 2.3.1
Summary: Personnel Roster
Home-page: https://github.com/collective/collective.roster
Author: Asko Soukka
Author-email: asko.soukka@iki.fi
License: EUPL
Platform: UNKNOWN
Classifier: Programming Language :: Python :: 2.7
Classifier: Framework :: Plone :: 4.3
Classifier: Framework :: Plone :: 5.0
Requires-Dist: setuptools
Requires-Dist: Products.CMFCore
Requires-Dist: Products.CMFPlone
Requires-Dist: Zope2
Requires-Dist: borg.localrole
Requires-Dist: plone.api
Requires-Dist: plone.app.dexterity
Requires-Dist: plone.app.textfield
Requires-Dist: plone.app.viewletmanager
Requires-Dist: plone.app.registry (>=1.2.5)
Requires-Dist: plone.autoform
Requires-Dist: plone.formwidget.contenttree
Requires-Dist: plone.formwidget.namedfile
Requires-Dist: plone.indexer
Requires-Dist: plone.memoize
Requires-Dist: plone.namedfile[blobs]
Requires-Dist: plone.supermodel
Requires-Dist: plone.z3ctable
Requires-Dist: python-magic
Requires-Dist: zope.component
Requires-Dist: zope.i18n
Requires-Dist: zope.i18nmessageid
Requires-Dist: zope.interface
Requires-Dist: zope.publisher
Requires-Dist: zope.schema
Provides-Extra: test
Requires-Dist: Pillow; extra == 'test'
Requires-Dist: corejet.core; extra == 'test'
Requires-Dist: plone.app.testing; extra == 'test'
Requires-Dist: plone.app.imaging; extra == 'test'
Requires-Dist: plone.app.robotframework; extra == 'test'
